hv/__init__.py
hv/cmd_ui.py
hv/ftd2xx_device.py
hv/ftdi_device.py
hv/hv_device.py
hv/run.py
hv/device_data/HT-6W.csv
hv/device_data/data_from_protocol.csv
hv/device_data/device_table.csv
hv/device_data/device_table_old.csv
hv/device_data/ftd2xx.dll
hv/ui/__init__.py
hv/ui/basic_setup.py
hv/ui/central_widget.py
hv/ui/device_list.py
hv/ui/hv_widget.py
hv/ui/indicator.py
hv/ui/main_window.py
hv/ui/oscilloscope.py
hv/ui/recorder.py
hv/ui/regulator.py
hv/ui/signal_generator.py
hv/ui/source_setup.py
hv/ui/utils.py
hv/ui/widgets.py
hv/ui/generators/__init__.py
hv/ui/generators/base.py
hv/ui/generators/custom.py
hv/ui/generators/rawtooth.py
hv/ui/generators/scanning.py
hv/ui/generators/square_wave.py
hv/ui/generators/stairs.py
hv/ui/generators/widgets.py
hv/ui/resources/basic_bolt.svg
hv/ui/resources/help.html
hv/ui/resources/material.css
hv/ui/resources/fonts/roboto/LICENSE
hv/ui/resources/fonts/roboto/Roboto-Black.ttf
hv/ui/resources/fonts/roboto/Roboto-BlackItalic.ttf
hv/ui/resources/fonts/roboto/Roboto-Bold.ttf
hv/ui/resources/fonts/roboto/Roboto-BoldItalic.ttf
hv/ui/resources/fonts/roboto/Roboto-Italic.ttf
hv/ui/resources/fonts/roboto/Roboto-Light.ttf
hv/ui/resources/fonts/roboto/Roboto-LightItalic.ttf
hv/ui/resources/fonts/roboto/Roboto-Medium.ttf
hv/ui/resources/fonts/roboto/Roboto-MediumItalic.ttf
hv/ui/resources/fonts/roboto/Roboto-Regular.ttf
hv/ui/resources/fonts/roboto/Roboto-Thin.ttf
hv/ui/resources/fonts/roboto/Roboto-ThinItalic.ttf
hv/ui/resources/fonts/roboto/RobotoCondensed-Bold.ttf
hv/ui/resources/fonts/roboto/RobotoCondensed-BoldItalic.ttf
hv/ui/resources/fonts/roboto/RobotoCondensed-Italic.ttf
hv/ui/resources/fonts/roboto/RobotoCondensed-Light.ttf
hv/ui/resources/fonts/roboto/RobotoCondensed-LightItalic.ttf
hv/ui/resources/fonts/roboto/RobotoCondensed-Regular.ttf
mipt_npm_hv_controls-0.2.2.dist-info/METADATA
mipt_npm_hv_controls-0.2.2.dist-info/WHEEL
mipt_npm_hv_controls-0.2.2.dist-info/entry_points.txt
mipt_npm_hv_controls-0.2.2.dist-info/top_level.txt
mipt_npm_hv_controls-0.2.2.dist-info/RECORD
