Metadata-Version: 2.1
Name: mipt-npm-hv-controls
Version: 0.2.2
Summary: Simple GUI for HV controls
Home-page: https://npm.mipt.ru/
Author: NPM Group
Author-email: mihail.zelenyy@phystech.edu
License: MIT License
Project-URL: Bug Tracker, https://github.com/mipt-npm/hv-controls
Project-URL: Documentation, https://github.com/mipt-npm/hv-controls
Project-URL: Source Code, https://github.com/mipt-npm/hv-controls
Keywords: hv
Platform: UNKNOWN
Classifier: Programming Language :: Python :: 3
Classifier: License :: OSI Approved :: MIT License
Classifier: Operating System :: OS Independent
Requires-Python: >=3.7
Requires-Dist: pyqt5
Requires-Dist: pyftdi
Requires-Dist: matplotlib
Requires-Dist: Jinja2
